eduimporter/XLSReader.py
eduimporter/__init__.py
eduimporter/constants.py
eduimporter/loggers.py
eduimporter/proxy.py
eduimporter/proxy_import.py
eduimporter/report.py
eduimporter/validators.py
testapp/__init__.py
testapp/manage.py
testapp/settings.py
testapp/urls.py
testapp/wsgi.py
testapp/app/__init__.py
testapp/app/models.py
testapp/app/tests/__init__.py
testapp/app/tests/test_report.py
testapp/app/tests/test_xlsreader.py
eduimporter-1.0.0.dist-info/LICENSE
eduimporter-1.0.0.dist-info/METADATA
eduimporter-1.0.0.dist-info/WHEEL
eduimporter-1.0.0.dist-info/top_level.txt
eduimporter-1.0.0.dist-info/RECORD
